postfixcalc/__init__.py
postfixcalc/calcobject.py
postfixcalc/parser.py
postfixcalc/py.typed
postfixcalc/pyeval.py
postfixcalc/typings.py
postfixcalc-0.8.4.dist-info/WHEEL
postfixcalc-0.8.4.dist-info/LICENSE
postfixcalc-0.8.4.dist-info/METADATA
postfixcalc-0.8.4.dist-info/RECORD
