Metadata-Version: 2.1
Name: postfixcalc
Version: 0.8.4
Summary: the stupid postfix evaluator
Home-page: https://github.com/mahdihaghverdi/postfixcalc
License: LICENSE
Keywords: parse,calculator,safe calculation,postfix
Author: Mahdi Haghverdi
Author-email: mahdihaghverdiliewpl@gmail.com
Requires-Python: >=3.10,<4.0
Classifier: Development Status :: 5 - Production/Stable
Classifier: Intended Audience :: Education
Classifier: License :: OSI Approved :: Apache Software License
Classifier: License :: Other/Proprietary License
Classifier: Operating System :: OS Independent
Classifier: Programming Language :: Python :: 3
Classifier: Programming Language :: Python :: 3.10
Classifier: Programming Language :: Python :: 3.11
Classifier: Programming Language :: Python :: 3
Classifier: Topic :: Education
Classifier: Topic :: Scientific/Engineering :: Mathematics
Classifier: Topic :: Software Development :: Libraries
Requires-Dist: black (>=22.12.0,<23.0.0)
Project-URL: Repository, https://github.com/mahdihaghverdi/postfixcalc
